{
    "photography": [
        {
            "possibility": "https:\/\/i.lensdump.com\/i\/AvmqHi.jpg"
        },
        {
            "possibility": "https:\/\/i.lensdump.com\/i\/Avauc1.jpg"
        },
        {
            "possibility": "https:\/\/cdn.discordapp.com\/attachments\/359859612918480897\/522356860586819586\/20180523_095816.jpg"
        },
        {
            "possibility": "https:\/\/cdn.discordapp.com\/attachments\/359859612918480897\/521609816204902411\/20181012_091619.jpg"
        },
        {
            "possibility": "https:\/\/cdn.discordapp.com\/attachments\/359859612918480897\/563942910995988491\/20190330_181520.jpg"
        },
        {
            "possibility": "https:\/\/cdn.discordapp.com\/attachments\/359859612918480897\/563942910995988490\/20190330_191754.jpg"
        },
        {
            "possibility": "https:\/\/cdn.discordapp.com\/attachments\/359859612918480897\/566491889390583818\/image0.jpg"
        },
        {
            "possibility": "https:\/\/cdn.discordapp.com\/attachments\/359859612918480897\/593321167365079070\/IMG_20190626_154453.jpg"
        },
        {
            "possibility": "https:\/\/cdn.discordapp.com\/attachments\/359859612918480897\/593321016449564672\/IMG_20190626_154903.jpg"
        }
    ]
}